HISTORY.txt
README.rst
setup.cfg
setup.py
openerp_bootstrap/__init__.py
openerp_bootstrap/newmodule.py
openerp_bootstrap/theme.py
openerp_bootstrap.egg-info/PKG-INFO
openerp_bootstrap.egg-info/SOURCES.txt
openerp_bootstrap.egg-info/dependency_links.txt
openerp_bootstrap.egg-info/entry_points.txt
openerp_bootstrap.egg-info/requires.txt
openerp_bootstrap.egg-info/top_level.txt
openerp_bootstrap.egg-info/zip-safe
openerp_bootstrap/templates/newmodule/__init__.py
openerp_bootstrap/templates/newmodule/__openerp__.py_tmpl
openerp_bootstrap/templates/theme/__init__.py
openerp_bootstrap/templates/theme/__openerp__.py_tmpl
openerp_bootstrap/templates/theme/static/css/+normalized_name+.css_tmpl
openerp_bootstrap/templates/theme/static/js/+normalized_name+.js_tmpl
openerp_bootstrap/templates/theme/static/xml/+normalized_name+.xml_tmpl