Metadata-Version: 1.0
Name: openerp-bootstrap
Version: 1.0a8
Summary: Easy bootstrap for your OpenERP modules
Home-page: https://github.com/simahawk/openerp_bootstrap
Author: Simone Orsi
Author-email: simone.orsi@domsense.com
License: GPL
Keywords: OpenERP paster
Platform: UNKNOWN
